cassio/__init__.py
cassio/py.typed
cassio/config/__init__.py
cassio/config/bundle_download.py
cassio/config/bundle_management.py
cassio/cql/__init__.py
cassio/db_extractor/__init__.py
cassio/db_extractor/cassandra_extractor.py
cassio/db_reader/__init__.py
cassio/db_reader/multi_table_cassandra_reader.py
cassio/history/__init__.py
cassio/history/history_management.py
cassio/history/stored_blob_history.py
cassio/inspection/__init__.py
cassio/inspection/schema.py
cassio/keyvalue/__init__.py
cassio/keyvalue/k_v_cache.py
cassio/keyvalue/kv_cache.py
cassio/table/__init__.py
cassio/table/base_table.py
cassio/table/cql.py
cassio/table/mixins.py
cassio/table/table_types.py
cassio/table/tables.py
cassio/table/utils.py
cassio/utils/__init__.py
cassio/utils/db_inspection/__init__.py
cassio/utils/vector/__init__.py
cassio/utils/vector/distance_metrics.py
cassio/vector/__init__.py
cassio/vector/vector_db_driver.py
cassio/vector/vector_table.py
cassio-0.1.5.dist-info/METADATA
cassio-0.1.5.dist-info/WHEEL
cassio-0.1.5.dist-info/entry_points.txt
cassio-0.1.5.dist-info/top_level.txt
cassio-0.1.5.dist-info/RECORD
