Metadata-Version: 2.1
Name: cassio
Version: 0.1.5
Summary: A framework-agnostic Python library to seamlessly integrate Apache Cassandra(R) with ML/LLM/genAI workloads.
Home-page: https://github.com/hemidactylus/cassio
Author: Stefano Lottini
Author-email: stefano.lottini@datastax.com
License: LICENSE.txt
Keywords: cassandra,ai,llm,genai,astradb
Platform: UNKNOWN
Classifier: Development Status :: 4 - Beta
Classifier: Intended Audience :: Developers
Classifier: License :: OSI Approved :: Apache Software License
Classifier: Programming Language :: Python :: 3
Classifier: Programming Language :: Python :: 3.8
Classifier: Programming Language :: Python :: 3.9
Classifier: Programming Language :: Python :: 3.10
Classifier: Programming Language :: Python :: 3.11
Classifier: Programming Language :: Python :: 3.12
Classifier: Programming Language :: Python :: 3 :: Only
Classifier: Topic :: Scientific/Engineering
Classifier: Topic :: Scientific/Engineering :: Artificial Intelligence
Requires-Python: >=3.8
